NseKit/Moneycontrol.py
NseKit/NseKit.py
NseKit/Useage.py
NseKit/__init__.py
nsekit-0.0.19.dist-info/licenses/LICENSE
nsekit-0.0.19.dist-info/METADATA
nsekit-0.0.19.dist-info/WHEEL
nsekit-0.0.19.dist-info/top_level.txt
nsekit-0.0.19.dist-info/RECORD
