Metadata-Version: 2.4
Name: NseKit
Version: 0.0.19
Summary: A Python package to fetch data from the National Stock Exchange (NSE) of India
Author-email: "Mr.Sad" <mr.xprasadx@gmail.com>
License: MIT License
Project-URL: Homepage, https://github.com/Prasad1612/NseKit
Project-URL: Repository, https://github.com/Prasad1612/NseKit.git
Classifier: Programming Language :: Python :: 3
Classifier: License :: OSI Approved :: MIT License
Classifier: Operating System :: OS Independent
Requires-Python: >=3.7
License-File: LICENSE
Requires-Dist: requests>=2.28.0
Requires-Dist: pandas>=1.5.0
Requires-Dist: numpy>=1.23.0
Requires-Dist: beautifulsoup4>=4.11.0
Requires-Dist: lxml>=4.9.0
Requires-Dist: xlrd>=2.0.0
Requires-Dist: openpyxl>=3.0.0
Requires-Dist: pyxlsb>=1.0.0
Requires-Dist: schedule>=1.2.2
Requires-Dist: rich>=14.2.0
Dynamic: license-file
